scrapy_redis_bloomfilter/__init__.py
scrapy_redis_bloomfilter/__version__.py
scrapy_redis_bloomfilter/bloomfilter.py
scrapy_redis_bloomfilter/defaults.py
scrapy_redis_bloomfilter/dupefilter.py
scrapy_redis_bloomfilter/scheduler.py
Scrapy_Redis_BloomFilter-0.8.1.dist-info/METADATA
Scrapy_Redis_BloomFilter-0.8.1.dist-info/WHEEL
Scrapy_Redis_BloomFilter-0.8.1.dist-info/top_level.txt
Scrapy_Redis_BloomFilter-0.8.1.dist-info/RECORD
