Metadata-Version: 2.1
Name: Scrapy-Redis-BloomFilter
Version: 0.8.1
Summary: Bloom Filter Support for Scrapy-Redis
Home-page: https://github.com/Python3WebSpider/ScrapyRedisBloomFilter
Author: Germey
Author-email: cqc@cuiqingcai.com
License: MIT
Platform: UNKNOWN
Classifier: License :: OSI Approved :: MIT License
Classifier: Programming Language :: Python :: 3.5
Classifier: Programming Language :: Python :: 3.6
Classifier: Programming Language :: Python :: 3.7
Classifier: Programming Language :: Python :: 3.8
Classifier: Programming Language :: Python :: Implementation :: CPython
Classifier: Programming Language :: Python :: Implementation :: PyPy
Requires-Python: >=3.5.0
